{
  "MenuDescriptions": {
    "start": "greeting",
    "help": "instructions",
    "update": "update decks",
    "lang": "toggle language | переключить язык",
    "new": "new game",
    "rates": "show rates",
    "images": "show images"
  },

  "StartFormat": {
    "Text": [
      "Hi! Here you can play Sensual Dares with your friends 😏",
      "Instructions: /help."
    ]
  },

  "HelpFormat": {
    "Text": [
      "Hi\\! Here you can play Sensual Dares with your friends 😏",
      "",
      "Draw *actions* one by one\\.",
      "You can decline performing an *action*\\. In that case, draw a *question* and answer it\\.",
      "",
      "",
      "{0}"
    ],
    "MarkdownV2": true
  },

  "CommandDescriptionFormat": {
    "Text": [
      "/{0} – {1}"
    ]
  },
  "StatusMessageStartFormat": {
    "Text": [
      "_{0}…_"
    ],
    "MarkdownV2": true
  },
  "StatusMessageEndFormat": {
    "Text": [
      "{0}{1}"
    ]
  },

  "StatusMessageEndSuccessFormat": {
    "Text": [
      " done.{0}"
    ]
  },

  "StatusMessageEndFailedFormat": {
    "Text": [
      " fail:",
      "{0}"
    ]
  },

  "Genders": {
    "Male": "Male",
    "Female": "Female",
    "Other": "Other"
  },

  "PartnersGenders": {
    "Male": "Males",
    "Female": "Females",
    "Other": "Others"
  },

  "JoinGameQrCaptionFormat": {
    "Text": [
      "{0}"
    ]
  },

  "NoPlayersYet": {
    "Text": [
      "There are no players yet."
    ]
  },

  "WrongGuid": {
    "Text": [
      "No game found for this code"
    ]
  },

  "NewPlayerGreeting": {
    "Text": [
      "Greetings!",
      "",
      "Kindly fill up your data:",
      "",
      "ℹ Below you can choose options already entered by others, or add your own."
    ]
  },

  "PlayerInfoFormat": {
    "Text": [
      "Name: {0}",
      "Gender: {1}",
      "People you want to interact with: {2}"
    ]
  },

  "Unknown": "❓",

  "EnterPlayerName": "Enter name",
  "EditPlayerName": "Edit name",

  "UpdatePlayerName": {
    "Text": [
      "Kindly enter your name:"
    ]
  },

  "NameIsPresent": {
    "Text": [
      "This name is already taken.",
      "Please enter a different one (for example, you can add a nickname or the letter of your last name):"
    ]
  },

  "DisplayNameFormat": "{0} @{1}",

  "ErrorFormat": "• {0}",
  "ErrorsSeparator": "\n",

  /*"NameAccepted": "🤝 Hello!",
  "NameChanageNeeded": "✍️ Запиши меня по-другому",*/

  /*"SelectGender": {
    "Text": [
      "Hello!",
      "Kindly choose your gender"
    ]
  },

  "SelectPartnersGenders": {
    "Text": [
      "Noted!",
      "Kindly choose gender(s) you want to interact with"
    ]
  },

  "Continue": "Continue",

  /*"NewPlayerGreetingFormat": {
    "Text": [
      "Hello, {0}!",
      "Kindly choose youe gender."
    ]
  },*/

  "PlayersFormat": {
    "Text": [
      "Players:",
      "{0}"
    ]
  },

  "NewGameStart": {
    "Text": [
      "🔥 New game started!"
    ]
  },
  "Accepted": {
    "Text": [
      "Accepted!"
    ]
  },
  "Refuse": {
    "Text": [
      "Can't update player list until card is completed."
    ]
  },

  "EquipmentPrefixFormat": {
    "Text": [
      "",
      "",
      "You will need:",
      "{0}"
    ]
  },

  "EquipmentFormat": "• {0}",
  "EquipmentSeparatorMessage": "\n",
  "EquipmentSeparatorSheet": ", ",

  "PlayerFormatActive": {
    "Text": [
      "{0}\\. `{1}`"
    ],
    "MarkdownV2": true
  },
  "PlayerFormatInactive": {
    "Text": [
      "_— {0}\\._ `{1}`"
    ],
    "MarkdownV2": true
  },

  "PlayersSeparator": "\n",

  "QuestionsTag": "❓",

  "Unreveal": "◀️",
  "Delete": "❌",

  "CurrentPlayerFormat": "{0} 👈",

  "ActivePlayerFormat": "✔️ {0}",
  "InactivePlayerFormat": "❌ {0}",
  "UndefinedPlayerFormat": "🔢 {0}",

  "Completed": "✅",

  "DrawCard": "🃏 Draw new card",

  "ActionCompletedPartially": "✔️",

  "TurnFormatFull": {
    "Text": [
      "*{1}* {0}{3}",
      "",
      "{2}"
    ],
    "MarkdownV2": true
  },

  "TurnFormatShort": {
    "Text": [
      "*{0}*{1}"
    ],
    "MarkdownV2": true
  },

  "TurnPartnersFormat": {
    "Text": [
      "",
      "",
      "{0}: {1}"
    ]
  },

  "CompletedCardFormat": {
    "Text": [
      "{0}",
      "",
      "{1}"
    ]
  },

  "Partner": "Partner",
  "Partners": "Partners",

  "DefaultSeparator": ", ",

  "CompatablePartnersSeparator": " + ",

  "UpdatePartsSeparator": ",",
  "UpdatePlayerSeparator": " ",
  "UpdateGroupsSeparator": "+",

  "ReadingDecks": {
    "Text": [
      "Reading decks"
    ]
  },

  "LangToggled": {
    "Text": [
      "Language switched to 🇬🇧"
    ]
  },

  "UpdatePlayersOperationDescription": {
    "Text": [
      "*список имён и предпочтений на новых строках* – изменить игроков\\. Игра начнётся или продолжится с первого и пойдёт по порядку\\."
    ],
    "MarkdownV2": true
  },

  "NothingChanges": {
    "Text": [
      "All players are the same."
    ]
  },

  "EndGameWarning": {
    "Text": [
      "Are you sure you ready to finish the game?"
    ]
  },

  "NoRates": {
    "Text": [
      "No one has rating yet."
    ]
  },
  "RatesFormat": {
    "Text": [
      "Ratings as of now:",
      "",
      "{0}"
    ]
  },
  "RateLineFormat": {
    "Text": [
      "• {0}"
    ]
  },
  "BestRateFormat": {
    "Text": [
      "*{0}*"
    ],
    "MarkdownV2": true
  },
  "RateFormat": {
    "Text": [
      "{0}: {3}✩, {4}↻ ||{1}✧ / {2}↑||"
    ],
    "MarkdownV2": true
  },
  "RateFormatHidden": {
    "Text": [
      "||{0}: {3}✩, {4}↻ {1}✧ / {2}↑||"
    ],
    "MarkdownV2": true
  },

  "WrongTagsFormat": "Decks ({0}) don't align with settings ({1}).",
  "WrongArrangementFormat": "Cards with ({0} {1}) found in ({2}) only."
}